LICENSE
MANIFEST.in
README.md
dev-requirements.txt
requirements.txt
setup.cfg
setup.py
project.d/README.md
project.d/classifiers.txt
project.d/pylint.cfg
project.d/skeleton_module.py
project.d/skeleton_testmodule.py
src/ok_deploy/__init__.py
src/ok_deploy/__main__.py
src/ok_deploy/_compat.py
src/ok_deploy.egg-info/PKG-INFO
src/ok_deploy.egg-info/SOURCES.txt
src/ok_deploy.egg-info/dependency_links.txt
src/ok_deploy.egg-info/entry_points.txt
src/ok_deploy.egg-info/not-zip-safe
src/ok_deploy.egg-info/requires.txt
src/ok_deploy.egg-info/top_level.txt