Metadata-Version: 1.1
Name: ok-deploy
Version: 0.1.0.dev20150322
Summary: OK Deploy – A continuous deployment pipeline implementation to transport applications to a runtime context using build-packs
Home-page: https://github.com/Feed-The-Web/ok-deploy
Author: Jürgen Hermann
Author-email: jh@web.de
License: Apache 2.0
Keywords: hosted.by.github,continuous.deployment,automation,build.packs,devops
Platform: UNKNOWN
Classifier: Development Status :: 2 - Pre-Alpha
Classifier: Intended Audience :: Developers
Classifier: License :: OSI Approved :: Apache 2.0
Classifier: Operating System :: OS Independent
Classifier: Programming Language :: Python :: 2
Classifier: Programming Language :: Python :: 2.7
Classifier: Programming Language :: Python :: 3
Classifier: Programming Language :: Python :: 3.4
